relational/__init__.py
relational/_nbdev.py
relational/core.py
relational-0.0.1.dist-info/LICENSE
relational-0.0.1.dist-info/METADATA
relational-0.0.1.dist-info/WHEEL
relational-0.0.1.dist-info/entry_points.txt
relational-0.0.1.dist-info/top_level.txt
relational-0.0.1.dist-info/RECORD
