Metadata-Version: 2.1
Name: relational
Version: 0.0.1
Summary: Minimal torch/numpy agnostic relational function.
Home-page: https://github.com/gngdb/relational/tree/master/
Author: Gavin Gray
Author-email: gngdb.labs@gmail.com
License: Apache Software License 2.0
Keywords: pytorch numpy relational
Platform: UNKNOWN
Classifier: Development Status :: 3 - Alpha
Classifier: Intended Audience :: Developers
Classifier: Natural Language :: English
Classifier: Programming Language :: Python :: 3.6
Classifier: Programming Language :: Python :: 3.7
Classifier: Programming Language :: Python :: 3.8
Classifier: License :: OSI Approved :: Apache Software License
Requires-Python: >=3.6
Requires-Dist: pip
Requires-Dist: packaging
Requires-Dist: einops
Provides-Extra: dev
